chubb_cog_helpers/metrics.py
chubb_cog_helpers/secret_locker.py
chubb_cog_helpers/supervised.py
chubb_cog_helpers-0.0.3.dist-info/LICENSE
chubb_cog_helpers-0.0.3.dist-info/METADATA
chubb_cog_helpers-0.0.3.dist-info/WHEEL
chubb_cog_helpers-0.0.3.dist-info/top_level.txt
chubb_cog_helpers-0.0.3.dist-info/RECORD
